git_migrator/__init__.py
git_migrator/__main__.py
git_migrator-1.0.3.dist-info/LICENSE
git_migrator-1.0.3.dist-info/METADATA
git_migrator-1.0.3.dist-info/WHEEL
git_migrator-1.0.3.dist-info/top_level.txt
git_migrator-1.0.3.dist-info/RECORD
