Metadata-Version: 2.1
Name: git_migrator
Version: 1.0.3
Summary: Migrate git repositories
Author-email: n4n5 <its.just.n4n5@gmail.com>
License: MIT License
Project-URL: Homepage, https://github.com/its-just-nans/git-migrator
Project-URL: Bug Tracker, https://github.com/its-just-nans/git-migrator/issues
Keywords: png,tools,cli
Classifier: License :: OSI Approved :: MIT License
Classifier: Programming Language :: Python
Classifier: Programming Language :: Python :: 3
Requires-Python: >=3.6
License-File: LICENSE
Requires-Dist: gitpython
